isimport/__init__.py
isimport/__main__.py
isimport-0.3.dist-info/LICENSE
isimport-0.3.dist-info/METADATA
isimport-0.3.dist-info/WHEEL
isimport-0.3.dist-info/top_level.txt
isimport-0.3.dist-info/RECORD
