Metadata-Version: 2.1
Name: isimport
Version: 0.3
Summary: Check required pip module for program.
Author: Ankush Bhagat (Ankush Bhagat)
Author-email: <ankushbhagatofficial@gmail.com>
Keywords: python,module,import,package,find
Classifier: Development Status :: 1 - Planning
Classifier: Intended Audience :: Developers
Classifier: Programming Language :: Python :: 3
Classifier: Operating System :: Unix
Classifier: Operating System :: MacOS :: MacOS X
Classifier: Operating System :: Microsoft :: Windows
License-File: LICENSE
Requires-Dist: rich
